davidkhala/ai/__init__.py
davidkhala/ai/model.py
davidkhala/ai/opik.py
davidkhala/ai/agent/README.md
davidkhala/ai/agent/__init__.py
davidkhala/ai/agent/langgraph.py
davidkhala/ai/agent/ragflow.py
davidkhala/ai/agent/dify/__init__.py
davidkhala/ai/agent/dify/const.py
davidkhala/ai/agent/dify/interface.py
davidkhala/ai/agent/dify/model.py
davidkhala/ai/agent/dify/api/__init__.py
davidkhala/ai/agent/dify/api/app.py
davidkhala/ai/agent/dify/api/knowledge.py
davidkhala/ai/agent/dify/ops/__init__.py
davidkhala/ai/agent/dify/ops/console/__init__.py
davidkhala/ai/agent/dify/ops/console/knowledge.py
davidkhala/ai/agent/dify/ops/console/plugin.py
davidkhala/ai/agent/dify/ops/console/session.py
davidkhala/ai/agent/dify/ops/db/__init__.py
davidkhala/ai/agent/dify/ops/db/app.py
davidkhala/ai/agent/dify/ops/db/knowledge.py
davidkhala/ai/agent/dify/ops/db/orm.py
davidkhala/ai/agent/dify/ops/db/sys.py
davidkhala/ai/agent/dify/plugins/__init__.py
davidkhala/ai/agent/dify/plugins/file.py
davidkhala/ai/agent/dify/plugins/firecrawl.py
davidkhala/ai/agent/dify/plugins/jina.py
davidkhala/ai/agent/dify/plugins/popular.py
davidkhala/ai/ali/__init__.py
davidkhala/ai/ali/agentbay.py
davidkhala/ai/ali/dashscope.py
davidkhala/ai/api/__init__.py
davidkhala/ai/api/openrouter.py
davidkhala/ai/api/siliconflow.py
davidkhala/ai/google/__init__.py
davidkhala/ai/google/adk.py
davidkhala/ai/google/gemini.py
davidkhala/ai/huggingface/BAAI.py
davidkhala/ai/huggingface/__init__.py
davidkhala/ai/huggingface/inference.py
davidkhala/ai/openai/__init__.py
davidkhala/ai/openai/azure.py
davidkhala/ai/openai/native.py
davidkhala/ai/openrouter/__init__.py
davidkhala_ai-0.2.0.dist-info/METADATA
davidkhala_ai-0.2.0.dist-info/WHEEL
davidkhala_ai-0.2.0.dist-info/RECORD
